opentelemetry/instrumentation/peewee/__init__.py
opentelemetry/instrumentation/peewee/package.py
opentelemetry/instrumentation/peewee/version.py
opentelemetry_instrumentation_peewee-0.57b0.dist-info/METADATA
opentelemetry_instrumentation_peewee-0.57b0.dist-info/WHEEL
opentelemetry_instrumentation_peewee-0.57b0.dist-info/entry_points.txt
opentelemetry_instrumentation_peewee-0.57b0.dist-info/RECORD
